Metadata-Version: 2.1
Name: Texture-Atlas
Version: 0.3.1
Summary: Create a texture dynamic texture atlas you can constantly change.
Home-page: https://github.com/ShaunKulesa/Texture-Atlas
Author: Shaun Kulesa
Author-email: shaunkulesa@gmail.com
License: MIT
Download-URL: https://github.com/ShaunKulesa/Texture-Atlas
Keywords: Texture Atlas
Platform: UNKNOWN
Classifier: Development Status :: 5 - Production/Stable
Classifier: Intended Audience :: Developers
Classifier: Topic :: Software Development :: Build Tools
Classifier: License :: OSI Approved :: MIT License
Classifier: Programming Language :: Python :: 3.10
Classifier: Programming Language :: Python :: 3.9
Classifier: Programming Language :: Python :: 3.8
Classifier: Programming Language :: Python :: 3.7
Classifier: Programming Language :: Python :: 3.6
Classifier: Programming Language :: Python :: 3.5
License-File: LICENSE.txt
